ansible_tools/__init__.py
ansible_tools/cli/__init__.py
ansible_tools/cli/ansible_local.py
ansible_tools/cli/ansible_mkpasswd.py
ansible_tools/cli/ansible_vault_helper.py
ansible_tools/cli/vaultify.py
ansible_tools-0.5.0.dist-info/METADATA
ansible_tools-0.5.0.dist-info/WHEEL
ansible_tools-0.5.0.dist-info/entry_points.txt
ansible_tools-0.5.0.dist-info/licenses/LICENSE.txt
ansible_tools-0.5.0.dist-info/RECORD
