Metadata-Version: 2.4
Name: ansible-tools
Version: 0.5.0
Summary: Keyring integration and local execution wrappers for Ansible
Project-URL: Homepage, https://github.com/lvillani/ansible-tools
Author-email: Lorenzo Villani <lorenzo@villani.me>
License-Expression: MIT
License-File: LICENSE.txt
Keywords: ansible,keyring,local,tools,wrapper
Classifier: Development Status :: 4 - Beta
Classifier: Environment :: Console
Classifier: Intended Audience :: System Administrators
Classifier: License :: OSI Approved :: MIT License
Classifier: Programming Language :: Python :: 3
Classifier: Programming Language :: Python :: 3.8
Classifier: Topic :: System :: Systems Administration
Requires-Python: >=3.8
Requires-Dist: keyring<26,>=25.5.0
Requires-Dist: passlib<2,>=1.7.4
